{
    "Name": "LumisteriaClothes-Shirt09",
    "Description": "A green and orange shirt",
	"FrontShirt": {
	"DisableGrayscale": true,
    "ColorMasks": [
      [ 254, 254, 254 ],
      [ 198, 198, 198 ]
    ],
    "SleeveColors": [
      [ 0, 45, 30 ],
      [ 0, 172, 100 ],
      [ 124, 228, 109 ]
    ],
    "StartingPosition": {
      "X": 0,
      "Y": 0
    },
    "BodyPosition": {
      "X": 0,
      "Y": 0
    },
    "ShirtSize": {
      "Width": 8,
      "Length": 8
    }
  },
  "RightShirt": {
	"DisableGrayscale": true,
    "ColorMasks": [
      [ 254, 254, 254 ],
      [ 198, 198, 198 ]
    ],
    "SleeveColors": [
      [ 0, 45, 30 ],
      [ 0, 172, 100 ],
      [ 124, 228, 109 ]
    ],
	"StartingPosition": {
	  "X": 0,
      "Y": 8
	},
	"BodyPosition": {
	  "X": 0,
      "Y": 0
    },
    "ShirtSize": {
      "Width": 8,
      "Length": 8
    }
  },
	"LeftShirt": {
	"DisableGrayscale": true,
    "ColorMasks": [
      [ 254, 254, 254 ],
      [ 198, 198, 198 ]
    ],
    "SleeveColors": [
      [ 0, 45, 30 ],
      [ 0, 172, 100 ],
      [ 124, 228, 109 ]
    ],
	"StartingPosition": {
      "X": 0,
      "Y": 16
    },
    "BodyPosition": {
      "X": 0,
      "Y": 0
    },
    "ShirtSize": {
      "Width": 8,
      "Length": 8
    }
  },
  "BackShirt": {
	"DisableGrayscale": true,
    "ColorMasks": [
      [ 254, 254, 254 ],
      [ 198, 198, 198 ]
    ],
    "SleeveColors": [
      [ 0, 45, 30 ],
      [ 0, 172, 100 ],
      [ 124, 228, 109 ]
    ],
    "StartingPosition": {
      "X": 0,
      "Y": 24
    },
    "BodyPosition": {
      "X": 0,
      "Y": 0
    },
    "ShirtSize": {
      "Width": 8,
      "Length": 8
    }
  }
}
