{
	"Changes": [
		
		// OUTFIT LOADS
	
		{
			"LogName": "Leo's Outfits",
			"Action": "EditImage",
			"Priority": "Late",
			"Target": "Portraits/ParrotBoy, Portraits/Leo_Spring, Portraits/Leo_Summer, Portraits/Leo_Winter, Portraits/Leo_FlowerDance, Portraits/Leo_SpiritsEve",
			"FromFile": "assets/Portraits/Leo/{{TargetWithoutPath}}.png"
		},
		
		{
			"LogName": "Leo's Sprite Outfits",
			"Action": "Load",
			"Priority": "High",
			"Target": "Characters/Leo_FlowerDance, Characters/Leo_SpiritsEve, Characters/Leo_Fall",
			"FromFile": "assets/Characters/Leo/{{TargetWithoutPath}}.png"
		},						
		
		//APPEARANCE DATA 
		{
			"LogName": "Leo Appearance Data",
			"Action": "EditData",
			"Target": "Data/Characters",
			"TargetField": ["Leo", "Appearance"],
			"Entries": {
								
				"Poltergeister.SeasonalCuteCharacters.LeoFall": {
					"Id": "Poltergeister.SeasonalCuteCharacters.LeoFall",
					"Condition": "SEASON Fall",
					"Sprite": "Characters/Leo_Fall",
					"Portrait": "Portraits/ParrotBoy",
					"Precedence": -120,
				},
				"{{ModId}}.LeoGingerIsland": {
					"Id": "{{ModId}}.LeoGingerIsland",
					"Condition": "!PLAYER_HAS_MAIL Host leoMoved",
					"Sprite": "Characters/Leo_Fall",
					"Portrait": "Portraits/ParrotBoy",
					"Precedence": -140,
				},				
			},
		},
		{
            "LogName": "Leo Calendar Sprite Edits",
            "Action": "EditImage",
            "Target": "Characters/ParrotBoy",
            "FromFile": "assets/Characters/Leo/Leo_Fall.png",
			"When": {"HasFlag |contains=leoMoved": false},
        },			
	]
}
