{
	"Changes": [
		
		// OUTFIT LOADS
		{
			"LogName": "Marnie's Outfits",
			"Action": "EditImage",
			"Priority": "Late",
			"Target": "Portraits/Marnie, Portraits/Marnie_Winter, Portraits/Marnie_Beach, Portraits/Marnie_Spring, Portraits/Marnie_Summer, Portraits/Marnie_Winter_Outdoor, Portraits/Marnie_FlowerDance, Portraits/Marnie_SpiritsEve, Portraits/Marnie_Aerobics",
			"FromFile": "assets/Portraits/Marnie/{{TargetWithoutPath}}.png"
		},
		{
			"LogName": "Marnie's Sprite Outfits",
			"Action": "Load",
			"Priority": "High",
			"Target": "Characters/Marnie_Spring, Characters/Marnie_Summer, Characters/Marnie_Fall, Characters/Marnie_Winter_Outdoor",
			"FromFile": "assets/Characters/Marnie/{{TargetWithoutPath}}.png"
		},					
		
		//APPEARANCE DATA 
		{
			"LogName": "Marnie Appearance Data",
			"Action": "EditData",
			"Target": "Data/Characters",
			"TargetField": ["Marnie", "Appearance"],
			"Fields": {
				
				"Poltergeister.SeasonalCuteCharacters.MarnieFall": {
					"Portrait": "Portraits/Marnie_Winter",
				},
				
				"Poltergeister.SeasonalCuteCharacters.MarnieWinterIndoor": {
					"Portrait": "Portraits/Marnie",
				},
			},
		},	
// MISCELLANEOUS		
		{
            "LogName": "Marnie Calendar Sprite Edits",
            "Action": "EditImage",
            "Target": "Characters/Marnie",
            "FromFile": "assets/Characters/Marnie/Marnie_Winter_Outdoor.png",
			"When": {"Season": "winter"}
        },	
		{
            "LogName": "Marnie Calendar Sprite Edits",
            "Action": "EditImage",
            "Target": "Characters/Marnie",
            "FromFile": "assets/Characters/Marnie/Marnie_Summer.png",
			"When": {"Season": "summer"}
        },	
		{
            "LogName": "Marnie Calendar Sprite Edits",
            "Action": "EditImage",
            "Target": "Characters/Marnie",
            "FromFile": "assets/Characters/Marnie/Marnie_Fall.png",
			"When": {"Season": "fall"}
        },	
		{
            "LogName": "Marnie Calendar Sprite Edits",
            "Action": "EditImage",
            "Target": "Characters/Marnie",
            "FromFile": "assets/Characters/Marnie/Marnie_Spring.png",
			"When": {"Season": "spring"}
        },			
	]
}
